jaxtro/__init__.py
jaxtro/main.py
jaxtro/models/__init__.py
jaxtro/models/wysocki2019massmodel.py
jaxtro/models/wysocki2019spinmodel.py
jaxtro/utils/__init__.py
jaxtro/utils/misc.py
jaxtro/utils/parser.py
jaxtro/utils/popgen.py
jaxtro-0.0.2.dist-info/LICENSE
jaxtro-0.0.2.dist-info/METADATA
jaxtro-0.0.2.dist-info/WHEEL
jaxtro-0.0.2.dist-info/entry_points.txt
jaxtro-0.0.2.dist-info/top_level.txt
jaxtro-0.0.2.dist-info/RECORD
